sphinx_api_relink/__init__.py
sphinx_api_relink/helpers.py
sphinx_api_relink/linkcode.py
sphinx_api_relink/py.typed
sphinx_api_relink/templates/module.rst.jinja
sphinx_api_relink/templates/package.rst.jinja
sphinx_api_relink/templates/toc.rst.jinja
sphinx_api_relink-0.0.12.dist-info/LICENSE
sphinx_api_relink-0.0.12.dist-info/METADATA
sphinx_api_relink-0.0.12.dist-info/WHEEL
sphinx_api_relink-0.0.12.dist-info/top_level.txt
sphinx_api_relink-0.0.12.dist-info/RECORD
